pyluba/__init__.py
pyluba/aliyun/cloud_gateway.py
pyluba/aliyun/cloud_service.py
pyluba/aliyun/dataclass/aep_response.py
pyluba/aliyun/dataclass/connect_response.py
pyluba/aliyun/dataclass/dev_by_account_response.py
pyluba/aliyun/dataclass/login_by_oauth_response.py
pyluba/aliyun/dataclass/regions_response.py
pyluba/aliyun/dataclass/session_by_authcode_response.py
pyluba/aliyun/tmp_constant.py
pyluba/bluetooth/__init__.py
pyluba/bluetooth/ble.py
pyluba/bluetooth/ble_message.py
pyluba/bluetooth/const.py
pyluba/bluetooth/data/__init__.py
pyluba/bluetooth/data/convert.py
pyluba/bluetooth/data/framectrldata.py
pyluba/bluetooth/data/notifydata.py
pyluba/const.py
pyluba/data/__init__.py
pyluba/data/model/__init__.py
pyluba/data/model/enums.py
pyluba/data/model/excute_boarder_params.py
pyluba/data/model/execute_boarder.py
pyluba/data/model/generate_route_information.py
pyluba/data/model/hash_list.py
pyluba/data/model/mowing_modes.py
pyluba/data/model/plan.py
pyluba/data/model/rapid_state.py
pyluba/data/model/region_data.py
pyluba/data/mqtt/__init__.py
pyluba/data/mqtt/event.py
pyluba/data/mqtt/properties.py
pyluba/data/mqtt/status.py
pyluba/event/__init__.py
pyluba/event/event.py
pyluba/http/_init_.py
pyluba/http/http.py
pyluba/luba/_init_.py
pyluba/luba/base.py
pyluba/mammotion/__init__.py
pyluba/mammotion/commands/__init__.py
pyluba/mammotion/commands/abstract_message.py
pyluba/mammotion/commands/mammotion_command.py
pyluba/mammotion/commands/messages/__init__.py
pyluba/mammotion/commands/messages/driver.py
pyluba/mammotion/commands/messages/media.py
pyluba/mammotion/commands/messages/navigation.py
pyluba/mammotion/commands/messages/navigation_old.py
pyluba/mammotion/commands/messages/network.py
pyluba/mammotion/commands/messages/ota.py
pyluba/mammotion/commands/messages/system.py
pyluba/mammotion/commands/messages/video.py
pyluba/mammotion/control/__init__.py
pyluba/mammotion/control/joystick.py
pyluba/mammotion/devices/__init__.py
pyluba/mammotion/devices/luba.py
pyluba-0.0.37.dist-info/LICENSE
pyluba-0.0.37.dist-info/METADATA
pyluba-0.0.37.dist-info/WHEEL
pyluba-0.0.37.dist-info/RECORD
