Metadata-Version: 2.1
Name: pyluba
Version: 0.0.37
Summary: 
License: GNU-3.0
Author: Michael Arthur
Author-email: michael@jumblesoft.co.nz
Requires-Python: >=3.11,<3.13
Classifier: License :: Other/Proprietary License
Classifier: Programming Language :: Python :: 3
Classifier: Programming Language :: Python :: 3.11
Classifier: Programming Language :: Python :: 3.12
Requires-Dist: aiohttp (>=3.9.1,<4.0.0)
Requires-Dist: alibabacloud-apigateway-util (>=0.0.2,<0.0.3)
Requires-Dist: alibabacloud-iot-api-gateway (>=0.0.4,<0.0.5)
Requires-Dist: alicloud-gateway-iot (>=1.0.0,<2.0.0)
Requires-Dist: aliyun-iot-linkkit (>=1.2.12,<2.0.0)
Requires-Dist: aliyun-python-sdk-iot (>=8.57.0,<9.0.0)
Requires-Dist: betterproto (>=1.2.5,<2.0.0)
Requires-Dist: bleak (>=0.21.0)
Requires-Dist: bleak-retry-connector (>=3.5.0,<4.0.0)
Requires-Dist: jsonic (>=1.0.0,<2.0.0)
Requires-Dist: mashumaro (>=3.13,<4.0)
Requires-Dist: nest-asyncio (>=1.6.0,<2.0.0)
Requires-Dist: orjson (>=3.9.15,<4.0.0)
Requires-Dist: paho-mqtt (>=1.6.1,<2.0.0)
Requires-Dist: protobuf (>=4.23.1)
Requires-Dist: py-jsonic (>=0.0.2,<0.0.3)
Requires-Dist: pyjoystick (>=1.2.4,<2.0.0)
